{
    "feeds": [
        {
            "title": "Today",
            "cards": [
                {
                    "title": "Sherleen commented on a post",
                    "text": "I eat sleep and work",
                    "avatar": "http://flipbit.co.uk/content/images/blog/build-avatar.jpg",
                    "createdon": 1434554728529,
                    "new": true,
                    "teacher": true
                },
                {
                    "title": "Sherleen commented on a post",
                    "text": "I eat sleep and workI eat sleep and workI eat sleep and workI eat sleep and workI eat sleep and workI eat sleep and workI eat sleep and workI eat sleep and workI eat sleep and workI eat sleep and workI eat sleep and work",
                    "avatar": "http://fdata.over-blog.net/4/12/25/66/avatar-blog-1194967266-tmpphptnjXqw.jpg",
                    "createdon": 1434554728529,
                    "new": false,
                    "teacher": true
                },
                {
                    "title": "You posted a message",
                    "text": "my horses are geeks",
                    "avatar": "http://static.comicvine.com/uploads/original/11118/111181237/3995061-avatar_dc75_batman.jpg",
                    "createdon": 1434554728529,
                    "new": false
                }
            ]
        },
        {
            "title": "Yesterday",
            "cards": [
                {
                    "title": "You posted a message",
                    "text": "my horses are geeks",
                    "avatar": "http://static.comicvine.com/uploads/original/11118/111181237/3995061-avatar_dc75_batman.jpg",
                    "createdon": 1434554728529,
                    "new": true
                },
                {
                    "title": "Jamie L replied to Cersy L",
                    "text": "lets breed or horses",
                    "avatar": "http://fdata.over-blog.net/4/12/25/66/avatar-blog-1194967266-tmpphptnjXqw.jpg",
                    "createdon": 1434554728529,
                    "new": false,
                    "teacher": true
                }
            ]
        },
        {
            "title": "April 15",
            "cards": [
                {
                    "title": "Jamie L replied to Cersy L",
                    "text": "lets breed or horses",
                    "avatar": "http://fdata.over-blog.net/4/12/25/66/avatar-blog-1194967266-tmpphptnjXqw.jpg",
                    "createdon": 1434554728529,
                    "new": false
                },
                {
                    "title": "You posted a message",
                    "text": "my horses are geeks",
                    "avatar": "http://static.comicvine.com/uploads/original/11118/111181237/3995061-avatar_dc75_batman.jpg",
                    "createdon": 1434554728529,
                    "new": false
                },
                {
                    "title": "Jamie L replied to Cersy L",
                    "text": "lets breed or horses",
                    "avatar": "http://i.imgur.com/A7Dy18f.png",
                    "createdon": 1434554728529,
                    "new": false,
                    "teacher": true
                }
            ]
        }
    ]
}