{
    "id": "12434dkjfdkf121",
    "name": "Ned Stark",
    "kids": [
        {
            "id": "6Wtua75DaiL4HoaC56456",
            "displayname":"Sansa S",
            "flag": "http://images.epals.com/flags/us.jpg",
            "location": "seattle, wa",
            "country": "United States",
            "avatar": "http://img3.rnkr-static.com/user_node_img/520/10387502/C100/sansa-stark-tv-characters-photo-u1.jpg"

        },
        {
            "id": "6Wtua75Da232323232r6",
            "displayname":"Rob S",
            "flag": "http://images.epals.com/flags/us.jpg",
            "location": "seattle, wa",
            "country": "United States",
            "avatar": "http://img4.wikia.nocookie.net/__cb20130726225228/cronacheghiacciofuoco/it/images/7/78/RobbStarkHD.png"
        },
        {
            "id": "645454545454fdfJJUKr6",
            "displayname":"Arya S",
            "flag": "http://images.epals.com/flags/us.jpg",
            "location": "miami, fl",
            "country": "United States",
            "avatar": "http://orig11.deviantart.net/13ac/f/2013/082/9/c/arya_stark_icon_by_cyborgvampire-d5z0wq0.jpg"
        },
        {
            "id": "6Wtua75DaidfdsfsdfKr6",
            "displayname":"Rickon S",
            "flag": "http://images.epals.com/flags/us.jpg",
            "location": "seattle, wa",
            "country": "United States",
            "avatar": "http://lorempixel.com/60/60/people/10"
        },
        {
            "id": "6Wtua75DaiL4H123456Kr6",
            "displayname": "Bran S",
            "flag": "http://images.epals.com/flags/us.jpg",
            "location": "seattle, wa",
            "country": "United States",
            "avatar": "http://lorempixel.com/60/60/people/11"
        }
    ]
}